resample_streamq/__init__.py
resample_streamq/resample_streamq.py
topnet_resampling-0.1.data/scripts/fix_streamq.sh
topnet_resampling-0.1.dist-info/LICENCE.txt
topnet_resampling-0.1.dist-info/METADATA
topnet_resampling-0.1.dist-info/WHEEL
topnet_resampling-0.1.dist-info/entry_points.txt
topnet_resampling-0.1.dist-info/top_level.txt
topnet_resampling-0.1.dist-info/RECORD
