Metadata-Version: 2.1
Name: topnet-resampling
Version: 0.1
Summary: Script to resample TopNet streamq time-series
Home-page: https://github.com/daniel-lagrava-niwa/topnet-resampling
Author: Daniel Lagrava
Author-email: daniel.lagravasandoval@niwa.co.nz
License: GNU
Platform: UNKNOWN
Requires-Dist: netCDF4
Requires-Dist: xarray
